livekit/plugins/ai_coustics/__init__.py
livekit/plugins/ai_coustics/_ffi.py
livekit/plugins/ai_coustics/log.py
livekit/plugins/ai_coustics/plugin.py
livekit/plugins/ai_coustics/plugins_ai_coustics_uniffi.dll
livekit_plugins_ai_coustics-0.1.6.dist-info/METADATA
livekit_plugins_ai_coustics-0.1.6.dist-info/WHEEL
livekit_plugins_ai_coustics-0.1.6.dist-info/top_level.txt
livekit_plugins_ai_coustics-0.1.6.dist-info/RECORD
