Metadata-Version: 2.4
Name: livekit-plugins-ai-coustics
Version: 0.1.6
Summary: LiveKit AI Coustics noise filtering plugin
License: SEE LICENSE IN https://livekit.io/legal/terms-of-service
Keywords: webrtc,realtime,audio,livekit,ai-coustics
Requires-Python: >=3.9
Requires-Dist: livekit>=0.21.3
